{
  "id": "ricciardo",
  "name": "Daniel Ricciardo",
  "code": "RIC",
  "number": "3",
  "nationality": "Australian",
  "races": [
    {
      "round": 1,
      "raceName": "Bahrain Grand Prix",
      "circuit": "Bahrain International Circuit",
      "position": 14,
      "q1": "1:30.562",
      "q2": "1:30.278",
      "q3": null,
      "constructor": "RB F1 Team"
    },
    {
      "round": 2,
      "raceName": "Saudi Arabian Grand Prix",
      "circuit": "Jeddah Corniche Circuit",
      "position": 14,
      "q1": "1:29.065",
      "q2": "1:29.025",
      "q3": null,
      "constructor": "RB F1 Team"
    },
    {
      "round": 3,
      "raceName": "Australian Grand Prix",
      "circuit": "Albert Park Grand Prix Circuit",
      "position": 18,
      "q1": "1:18.085",
      "q2": null,
      "q3": null,
      "constructor": "RB F1 Team"
    },
    {
      "round": 4,
      "raceName": "Japanese Grand Prix",
      "circuit": "Suzuka Circuit",
      "position": 11,
      "q1": "1:29.727",
      "q2": "1:29.472",
      "q3": null,
      "constructor": "RB F1 Team"
    },
    {
      "round": 5,
      "raceName": "Chinese Grand Prix",
      "circuit": "Shanghai International Circuit",
      "position": 12,
      "q1": "1:35.443",
      "q2": "1:34.934",
      "q3": null,
      "constructor": "RB F1 Team"
    },
    {
      "round": 6,
      "raceName": "Miami Grand Prix",
      "circuit": "Miami International Autodrome",
      "position": 18,
      "q1": "1:28.617",
      "q2": null,
      "q3": null,
      "constructor": "RB F1 Team"
    },
    {
      "round": 7,
      "raceName": "Emilia Romagna Grand Prix",
      "circuit": "Autodromo Enzo e Dino Ferrari",
      "position": 9,
      "q1": "1:16.060",
      "q2": "1:15.691",
      "q3": "1:15.674",
      "constructor": "RB F1 Team"
    },
    {
      "round": 8,
      "raceName": "Monaco Grand Prix",
      "circuit": "Circuit de Monaco",
      "position": 12,
      "q1": "1:11.785",
      "q2": "1:11.482",
      "q3": null,
      "constructor": "RB F1 Team"
    },
    {
      "round": 9,
      "raceName": "Canadian Grand Prix",
      "circuit": "Circuit Gilles Villeneuve",
      "position": 5,
      "q1": "1:13.240",
      "q2": "1:12.572",
      "q3": "1:12.178",
      "constructor": "RB F1 Team"
    },
    {
      "round": 10,
      "raceName": "Spanish Grand Prix",
      "circuit": "Circuit de Barcelona-Catalunya",
      "position": 18,
      "q1": "1:13.075",
      "q2": null,
      "q3": null,
      "constructor": "RB F1 Team"
    },
    {
      "round": 11,
      "raceName": "Austrian Grand Prix",
      "circuit": "Red Bull Ring",
      "position": 11,
      "q1": "1:05.569",
      "q2": "1:05.289",
      "q3": null,
      "constructor": "RB F1 Team"
    },
    {
      "round": 12,
      "raceName": "British Grand Prix",
      "circuit": "Silverstone Circuit",
      "position": 15,
      "q1": "1:31.291",
      "q2": "1:27.949",
      "q3": null,
      "constructor": "RB F1 Team"
    },
    {
      "round": 13,
      "raceName": "Hungarian Grand Prix",
      "circuit": "Hungaroring",
      "position": 9,
      "q1": "1:17.050",
      "q2": "1:16.202",
      "q3": "1:16.447",
      "constructor": "RB F1 Team"
    },
    {
      "round": 14,
      "raceName": "Belgian Grand Prix",
      "circuit": "Circuit de Spa-Francorchamps",
      "position": 13,
      "q1": "1:55.451",
      "q2": "1:54.682",
      "q3": null,
      "constructor": "RB F1 Team"
    },
    {
      "round": 15,
      "raceName": "Dutch Grand Prix",
      "circuit": "Circuit Park Zandvoort",
      "position": 15,
      "q1": "1:11.943",
      "q2": null,
      "q3": null,
      "constructor": "RB F1 Team"
    },
    {
      "round": 16,
      "raceName": "Italian Grand Prix",
      "circuit": "Autodromo Nazionale di Monza",
      "position": 12,
      "q1": "1:20.901",
      "q2": "1:20.479",
      "q3": null,
      "constructor": "RB F1 Team"
    },
    {
      "round": 17,
      "raceName": "Azerbaijan Grand Prix",
      "circuit": "Baku City Circuit",
      "position": 15,
      "q1": "1:43.547",
      "q2": null,
      "q3": null,
      "constructor": "RB F1 Team"
    },
    {
      "round": 18,
      "raceName": "Singapore Grand Prix",
      "circuit": "Marina Bay Street Circuit",
      "position": 16,
      "q1": "1:31.085",
      "q2": null,
      "q3": null,
      "constructor": "RB F1 Team"
    }
  ],
  "stats": {
    "totalRaces": 18,
    "polePositions": 0,
    "avgQualifyingPosition": "13.17",
    "bestQualifyingPosition": 5
  }
}